README.md
setup.cfg
setup.py
r360_py/__init__.py
r360_py.egg-info/PKG-INFO
r360_py.egg-info/SOURCES.txt
r360_py.egg-info/dependency_links.txt
r360_py.egg-info/requires.txt
r360_py.egg-info/top_level.txt
r360_py/cli/__init__.py
r360_py/cli/__main__.py
r360_py/rest/ServiceExecutor.py
r360_py/rest/__init__.py
r360_py/util/Configuration.py
r360_py/util/TravelOptions.py
r360_py/util/Util.py
r360_py/util/__init__.py
r360_py/util/enum/EdgeWeightType.py
r360_py/util/enum/PathSerializerType.py
r360_py/util/enum/PolygonIntersectionMode.py
r360_py/util/enum/PolygonSerializationType.py
r360_py/util/enum/TravelType.py
r360_py/util/enum/__init__.py