Metadata-Version: 1.1
Name: r360-py
Version: 0.20
Summary: A python client library to query the Route360° API
Home-page: https://github.com/route360/r360-py
Author: Motion Intelligence GmbH
Author-email: mail@motionintelligence.net
License: UNKNOWN
Download-URL: https://github.com/route360/r360-py/tarball/0.20
Keywords: isochrone,routing,polygon,openstreetmaps,gtfs,map
Platform: UNKNOWN
